LICENSE.md
MANIFEST.in
README.md
setup.py
HolmesIV.egg-info/PKG-INFO
HolmesIV.egg-info/SOURCES.txt
HolmesIV.egg-info/dependency_links.txt
HolmesIV.egg-info/entry_points.txt
HolmesIV.egg-info/requires.txt
HolmesIV.egg-info/top_level.txt
mycroft/__init__.py
mycroft/api/__init__.py
mycroft/audio/__init__.py
mycroft/audio/__main__.py
mycroft/audio/audioservice.py
mycroft/audio/interface.py
mycroft/audio/speech.py
mycroft/audio/utils.py
mycroft/audio/services/__init__.py
mycroft/audio/services/chromecast/__init__.py
mycroft/audio/services/mopidy/__init__.py
mycroft/audio/services/mopidy/mopidypost.py
mycroft/audio/services/mplayer/__init__.py
mycroft/audio/services/simple/__init__.py
mycroft/audio/services/vlc/__init__.py
mycroft/client/__init__.py
mycroft/client/enclosure/__init__.py
mycroft/client/enclosure/__main__.py
mycroft/client/enclosure/base.py
mycroft/client/enclosure/generic/__init__.py
mycroft/client/enclosure/mark1/__init__.py
mycroft/client/enclosure/mark1/arduino.py
mycroft/client/enclosure/mark1/eyes.py
mycroft/client/enclosure/mark1/mouth.py
mycroft/client/enclosure/mark2/__init__.py
mycroft/client/speech/__init__.py
mycroft/client/speech/__main__.py
mycroft/client/speech/data_structures.py
mycroft/client/speech/hotword_factory.py
mycroft/client/speech/listener.py
mycroft/client/speech/mic.py
mycroft/client/speech/word_extractor.py
mycroft/client/text/__init__.py
mycroft/client/text/__main__.py
mycroft/client/text/gui_server.py
mycroft/client/text/text_client.py
mycroft/configuration/__init__.py
mycroft/configuration/config.py
mycroft/configuration/locale.py
mycroft/configuration/locations.py
mycroft/configuration/mycroft.conf
mycroft/dialog/__init__.py
mycroft/dialog/dialog.py
mycroft/enclosure/__init__.py
mycroft/enclosure/api.py
mycroft/enclosure/display_manager.py
mycroft/enclosure/gui.py
mycroft/filesystem/__init__.py
mycroft/identity/__init__.py
mycroft/lock/__init__.py
mycroft/messagebus/__init__.py
mycroft/messagebus/load_config.py
mycroft/messagebus/message.py
mycroft/messagebus/send.py
mycroft/messagebus/send_func.py
mycroft/messagebus/client/__init__.py
mycroft/messagebus/client/client.py
mycroft/messagebus/service/__init__.py
